docs/draw.io_set_link.png
sphinxcontrib_svg_links/__init__.py
sphinxcontrib_svg_links/extension.py
sphinxcontrib_svg_links/svg.py
sphinxcontrib_svg_links/writer.py
sphinxcontrib_svg_links-0.1.7.dist-info/LICENSE
sphinxcontrib_svg_links-0.1.7.dist-info/METADATA
sphinxcontrib_svg_links-0.1.7.dist-info/WHEEL
sphinxcontrib_svg_links-0.1.7.dist-info/RECORD
